lcci/__init__.py
lcci/agent.py
lcci/configuration.py
lcci/main.py
lcci/tools.py
lcci/version.py
lcci-2017.1rc6.dist-info/DESCRIPTION.rst
lcci-2017.1rc6.dist-info/METADATA
lcci-2017.1rc6.dist-info/RECORD
lcci-2017.1rc6.dist-info/WHEEL
lcci-2017.1rc6.dist-info/entry_points.txt
lcci-2017.1rc6.dist-info/metadata.json
lcci-2017.1rc6.dist-info/top_level.txt
