Metadata-Version: 2.0
Name: lcci
Version: 2017.1rc6
Summary: LibreCores.org Continuous Integration tool
Home-page: https://github.com/librecores/lcci-python
Author: LibreCores.org developer
Author-email: dev@lists.librecores.org
License: MIT
Keywords: librecores ci tool
Platform: UNKNOWN
Classifier: Development Status :: 3 - Alpha
Classifier: Intended Audience :: Developers
Classifier: Topic :: Software Development :: Build Tools
Classifier: License :: OSI Approved :: MIT License
Classifier: Programming Language :: Python :: 2
Classifier: Programming Language :: Python :: 2.7
Classifier: Programming Language :: Python :: 3
Classifier: Programming Language :: Python :: 3.3
Classifier: Programming Language :: Python :: 3.4
Classifier: Programming Language :: Python :: 3.5
Requires-Dist: PyGithub
Requires-Dist: docker
Requires-Dist: pyaml
